simple_duck_ml/__init__.py
simple_duck_ml/activations/i_activation.py
simple_duck_ml/activations/relu_activation.py
simple_duck_ml/activations/softmax_activation.py
simple_duck_ml/container.py
simple_duck_ml/dataset_unpacker/bin_dataset_unpacker.py
simple_duck_ml/dataset_unpacker/dataset.py
simple_duck_ml/dataset_unpacker/i_dataset_unpacker.py
simple_duck_ml/io/i_layer_writer.py
simple_duck_ml/io/toml_layer_writer.py
simple_duck_ml/layers/convolutional_layer.py
simple_duck_ml/layers/dense_layer.py
simple_duck_ml/layers/flatten_layer.py
simple_duck_ml/layers/i_layer.py
simple_duck_ml/loss/cross_entropy_loss.py
simple_duck_ml/loss/i_loss.py
simple_duck_ml/loss/mse_loss.py
simple_duck_ml/models/model.py
simple_duck_ml/serializers/create_dir.py
simple_duck_ml/serializers/tensor_io.py
simple_duck_ml/serializers/toml_io.py
simple_duck_ml-0.1.11.dist-info/METADATA
simple_duck_ml-0.1.11.dist-info/WHEEL
simple_duck_ml-0.1.11.dist-info/RECORD
