Metadata-Version: 2.3
Name: simple_duck_ml
Version: 0.1.11
Summary: 🦆 A minimal Ml library for Python
Author: Phe Pato
Author-email: pheprogrammer@gmail.com
Requires-Python: >=3.12
Classifier: Programming Language :: Python :: 3
Classifier: Programming Language :: Python :: 3.12
Classifier: Programming Language :: Python :: 3.13
Requires-Dist: duckdi (>=0.1.13,<0.2)
Requires-Dist: graphviz (>=0.20.3,<0.21.0)
Requires-Dist: numpy (>=2.2.5,<3.0.0)
Requires-Dist: opencv-python (>=4.11.0.86,<5.0.0.0)
Requires-Dist: pydantic (>=2.11.4,<3.0.0)
Requires-Dist: toml (>=0.10.2,<0.11.0)
Requires-Dist: tqdm (>=4.67.1,<5.0.0)
Project-URL: Homepage, https://pypi.org/project/simple_duck_ml
Project-URL: Repository, https://github.com/PheFreire/SimpleDuckMl
